{
    "Noah": "2-1",
    "Luca": "2-1",
    "Lucas": "2-1",
    "Liam": "1-1",
    "Sem": "1-1",
    "Mees": "1-1",
    "Noud": "1-1",
    "Levi": "2-1",
    "James": "1-1",
    "Adam": "2-1",
    "Finn": "1-1",
    "Daan": "1-1",
    "Sam": "1-1",
    "Milan": "2-1",
    "Luuk": "1-1",
    "Guus": "1-1",
    "Zayn": "1-1",
    "Mats": "1-1",
    "Mason": "2-1",
    "Bram": "1-1",
    "Siem": "1-1",
    "Boaz": "2-1",
    "Oliver": "3-1",
    "Olivier": "3-1",
    "Benjamin": "3-1",
    "Gijs": "1-1",
    "Floris": "2-1",
    "Jesse": "2-1",
    "Joep": "1-1",
    "Teun": "1-1",
    "Otis": "2-1",
    "Jake": "1-1",
    "Lio": "1-1",
    "Morris": "2-1",
    "Moos": "1-1",
    "Jens": "1-1",
    "Ties": "1-1",
    "Elias": "3-1",
    "Abel": "2-1",
    "Owen": "2-1",
    "Thomas": "2-1",
    "Ted": "1-1",
    "Max": "1-1",
    "David": "2-1",
    "Julian": "3-1",
    "Jan": "1-1",
    "Mohammed": "3-2",
    "Jurre": "2-1",
    "Tobias": "3-1",
    "Kai": "1-1",
    "Hugo": "2-1",
    "Thijs": "1-1",
    "Mick": "1-1",
    "Lars": "1-1",
    "Fedde": "2-1",
    "Hidde": "2-1",
    "Joah": "2-1",
    "Nolan": "2-1",
    "Melle": "2-1",
    "Rayan": "2-1",
    "Jip": "1-1",
    "Willem": "2-1",
    "Loek": "1-1",
    "Samuel": "3-1",
    "Dean": "1-1",
    "Nathan": "2-1",
    "Milo": "2-1",
    "Jace": "1-1",
    "Sepp": "1-1",
    "Stijn": "1-1",
    "Tom": "1-1",
    "Oscar": "2-1",
    "Louis": "2-2",
    "Tijn": "1-1",
    "Jack": "1-1",
    "Aiden": "2-1",
    "Ezra": "2-1",
    "Alexander": "4-3",
    "Lenn": "1-1",
    "Sven": "1-1",
    "Amir": "2-2",
    "Vince": "1-1",
    "Scott": "1-1",
    "Cas": "1-1",
    "Matteo": "3-2",
    "Wout": "1-1",
    "Xavi": "2-1",
    "Boris": "2-1",
    "Jayden": "2-1",
    "Mohamed": "3-2",
    "Pepijn": "2-2",
    "Arthur": "2-1",
    "Omar": "2-1",
    "Ibrahim": "3-1",
    "Ryan": "2-1",
    "Joshua": "3-1",
    "Dex": "1-1",
    "Job": "1-1",
    "Sef": "1-1",
    "Niek": "1-1",
    "Dani": "2-1",
    "Mateo": "3-2",
    "Charlie": "2-1",
    "Musa": "2-1",
    "Quinn": "1-1",
    "Roan": "2-1",
    "Ruben": "2-1",
    "Jaxx": "1-1",
    "Lowen": "2-1",
    "Hamza": "2-1",
    "Jason": "2-1",
    "Frenkie": "2-1",
    "Johannes": "3-2",
    "Lewis": "2-1",
    "Felix": "2-1",
    "Zayd": "1-1",
    "Louay": "2-1",
    "Luka": "2-1",
    "Joes": "1-1",
    "Senn": "1-1",
    "Pim": "1-1",
    "Joris": "2-1",
    "Sep": "1-1",
    "Leo": "2-1",
    "Lukas": "2-1",
    "Odin": "2-1",
    "Jonah": "2-1",
    "Leon": "1-1",
    "Elijah": "3-2",
    "Aaron": "2-1",
    "Logan": "2-1",
    "Sev": "1-1",
    "No": "1-1",
    "Aron": "2-1",
    "Bodhi": "2-1",
    "Jules": "1-1",
    "Muhammed": "3-2",
    "Philip": "2-1",
    "Alex": "2-1",
    "Duuk": "1-1",
    "Jonas": "2-1",
    "Laurens": "2-1",
    "Julius": "3-1",
    "Mace": "1-1",
    "Pieter": "2-1",
    "Imran": "2-1",
    "Joas": "2-1",
    "Casper": "2-1",
    "Jacob": "2-1",
    "Ali": "2-1",
    "Ace": "1-1",
    "Tim": "1-1",
    "Youssef": "2-1",
    "Jo": "1-1",
    "Manuel": "3-1",
    "Rens": "1-1",
    "Yusuf": "2-1",
    "Daniel": "3-1",
    "Florian": "3-1",
    "Oos": "1-1",
    "Ravi": "2-1",
    "Jelle": "2-1",
    "Miles": "1-1",
    "Hendrik": "2-1",
    "Ilyas": "3-1",
    "Simon": "2-1",
    "Stef": "1-1",
    "Rafael": "3-1",
    "Raf": "1-1",
    "Sami": "2-1",
    "Ayden": "2-1",
    "Miran": "2-1",
    "Kees": "1-1",
    "Jax": "1-1",
    "Harvey": "2-1",
    "Stan": "1-1",
    "Jim": "1-1",
    "Jonathan": "3-1",
    "Louie": "2-2",
    "Kyan": "2-1",
    "Lev": "1-1",
    "Thijmen": "2-1",
    "Ayaz": "2-2",
    "Joa": "1-1",
    "Lex": "1-1",
    "Muhammad": "3-2",
    "Cody": "2-1",
    "Isaiah": "3-2",
    "Emir": "2-2",
    "Bob": "1-1",
    "Kaj": "1-1",
    "Maxim": "2-2",
    "Mayson": "2-1",
    "Sil": "1-1",
    "Aras": "2-1",
    "Beau": "1-1",
    "Lou": "1-1",
    "Moussa": "2-1",
    "Victor": "2-1",
    "Seth": "1-1",
    "Tygo": "2-1",
    "Faas": "1-1",
    "Kian": "2-1",
    "Mika": "2-1",
    "Joe": "1-1",
    "Zakaria": "3-2",
    "Bodi": "2-1",
    "Gabriel": "3-1",
    "George": "1-1",
    "Micha": "2-1",
    "Riv": "1-1",
    "Jari": "2-1",
    "Jamie": "2-1",
    "Yves": "2-2",
    "Idris": "2-1",
    "Juda": "2-1",
    "Loet": "1-1",
    "Luc": "1-1",
    "Novan": "2-1",
    "Olaf": "2-1",
    "Ben": "1-1",
    "Cornelis": "3-2",
    "Dante": "2-1",
    "Jort": "1-1",
    "Kay": "1-1",
    "Luke": "1-1",
    "Vigo": "2-1",
    "Ayoub": "2-2",
    "Mark": "1-1",
    "Ole": "2-1",
    "Zeyd": "1-1",
    "Lux": "1-1",
    "Jelte": "2-1",
    "Jeppe": "2-1",
    "Jasper": "2-1",
    "Tommy": "2-1",
    "Bowie": "2-1",
    "Gerrit": "2-1",
    "Koen": "1-1",
    "Toon": "1-1",
    "Ahmed": "2-1",
    "Damian": "3-1",
    "Mahir": "2-2",
    "Mohammad": "3-2",
    "Nino": "2-1",
    "Boet": "1-1",
    "Dylan": "2-1",
    "Jay": "1-1",
    "Jayce": "1-1",
    "Malik": "2-2",
    "Mart": "1-1",
    "Nouri": "2-1",
    "Riley": "2-1",
    "Ivan": "2-1",
    "Robin": "2-1",
    "Isa": "2-1",
    "Matthias": "3-2",
    "Otto": "2-1",
    "Tobi": "2-1",
    "Vic": "1-1",
    "Zion": "2-1",
    "Evan": "2-1",
    "Ian": "2-1",
    "Isaac": "2-1",
    "Manu": "2-2",
    "Mylo": "2-1",
    "Eden": "2-1",
    "Fabian": "3-1",
    "Pelle": "2-1",
    "Ethan": "2-1",
    "Gabri": "2-1",
    "Rein": "1-1",
    "Vik": "1-1",
    "Duco": "2-1",
    "Kaan": "1-1",
    "Younes": "2-1",
    "Amin": "2-2",
    "Aslan": "2-1",
    "Jona": "2-1",
    "Mert": "1-1",
    "Yahya": "2-1",
    "Filip": "2-1",
    "Maas": "1-1",
    "Berend": "2-1",
    "Elio": "3-1",
    "Javi": "2-1",
    "Maurits": "2-1",
    "Nikodem": "3-1",
    "Flynn": "1-1",
    "Jur": "1-1",
    "Twan": "1-1",
    "Len": "1-1",
    "Ralph": "1-1",
    "Sebastiaan": "3-2",
    "Timo": "2-1",
    "Fynn": "1-1",
    "Rowan": "2-1",
    "Tyler": "2-1",
    "Eli": "2-1",
    "Huub": "1-1",
    "Tibbe": "2-1",
    "Bas": "1-1",
    "Benja": "2-1",
    "Daley": "2-1",
    "Dirk": "1-1",
    "Ivar": "2-1",
    "Jesper": "2-1",
    "Joey": "2-1",
    "Kerem": "2-2",
    "Noan": "2-1",
    "Valentijn": "3-1",
    "Bobby": "2-1",
    "Dayn": "1-1",
    "Klaas": "1-1",
    "Naud": "1-1",
    "Ahmad": "2-1",
    "Niels": "1-1",
    "William": "3-1",
    "Colin": "2-1",
    "Lasse": "2-1",
    "Mike": "1-1",
    "Nick": "1-1",
    "Raff": "1-1",
    "Riff": "1-1",
    "Sebastian": "4-2",
    "Tuur": "1-1",
    "Bruno": "2-1",
    "Thijn": "1-1",
    "Zakariya": "4-3",
    "Boas": "2-1",
    "Deniz": "2-1",
    "Levy": "2-1",
    "Mustafa": "3-1",
    "Naoufal": "2-2",
    "Theo": "2-1",
    "Brent": "1-1",
    "Leonardo": "4-3",
    "Lorenzo": "3-2",
    "Quinten": "2-1",
    "Seppe": "2-1",
    "Siebe": "2-1",
    "Sten": "1-1",
    "Abe": "2-1",
    "Atlas": "2-1",
    "Foss": "1-1",
    "Jackson": "2-1",
    "Julan": "2-1",
    "Louen": "2-2",
    "Luan": "2-1",
    "Mads": "1-1",
    "Natan": "2-1",
    "Oskar": "2-1",
    "Safouan": "2-2",
    "Arda": "2-1",
    "Dave": "1-1",
    "Jordan": "2-1",
    "Kasper": "2-1",
    "Liyam": "2-1",
    "Matthijs": "2-2",
    "Novi": "2-1",
    "Davi": "2-1",
    "Don": "1-1",
    "Jop": "1-1",
    "Sebas": "2-2",
    "Seff": "1-1",
    "Toby": "2-1",
    "Yuki": "2-1",
    "Enzo": "2-1",
    "Ferre": "2-1",
    "Junayd": "2-1",
    "Justin": "2-1",
    "Lieuwe": "2-1",
    "Maeson": "2-1",
    "Midas": "2-1",
    "Mira": "2-1",
    "Savi": "2-1",
    "Seb": "1-1",
    "Thiago": "2-2",
    "Albert": "2-1",
    "Donny": "2-1",
    "Sverre": "2-1",
    "Abdullah": "3-2",
    "Alparslan": "3-1",
    "Ayman": "2-1",
    "Davey": "2-1",
    "Dez": "1-1",
    "Eymen": "2-1",
    "Jayson": "2-1",
    "Jidde": "2-1",
    "Josh": "1-1",
    "Karam": "2-2",
    "Kylian": "3-1",
    "Marcus": "2-1",
    "Remi": "2-1",
    "Senne": "2-1",
    "Tijs": "1-1",
    "Wes": "1-1",
    "Boyd": "1-1",
    "Fijs": "1-1",
    "Karel": "2-1",
    "Lias": "2-1",
    "Marley": "2-1",
    "Michael": "2-1",
    "Revi": "2-1",
    "Xavier": "2-2",
    "Douwe": "2-1",
    "Fender": "2-1",
    "Fos": "1-1",
    "Jaivey": "2-1",
    "Marijn": "2-2",
    "Matthew": "2-1",
    "Mex": "1-1",
    "Nox": "1-1",
    "Collin": "2-1",
    "Dion": "2-2",
    "Elliot": "3-1",
    "Ivo": "2-1",
    "Jimi": "2-1",
    "Kane": "1-1",
    "Mels": "1-1",
    "Reza": "2-1",
    "Alan": "2-2",
    "Ayaan": "2-1",
    "Chris": "1-1",
    "Diego": "2-1",
    "Giovanni": "3-2",
    "Ismail": "3-1",
    "Jimmy": "2-1",
    "Johan": "2-1",
    "Joppe": "2-1",
    "Reda": "2-1",
    "Rijk": "1-1",
    "Tijmen": "2-1",
    "Tristan": "2-1",
    "Youp": "1-1",
    "Zain": "2-2",
    "Arie": "2-1",
    "Finnley": "2-1",
    "Ilias": "3-1",
    "Lyam": "1-1",
    "Marinus": "3-2",
    "Raphael": "3-1",
    "Teije": "2-1",
    "Viggo": "2-1",
    "Viktor": "2-1",
    "Aleksander": "4-3",
    "Anas": "2-2",
    "Archie": "2-1",
    "Freek": "1-1",
    "Issa": "2-1",
    "Judah": "2-1",
    "Marcel": "2-1",
    "Mik": "1-1",
    "Nouh": "1-1",
    "Quin": "1-1",
    "Rapha": "2-1",
    "Robert": "2-1",
    "Soy": "1-1",
    "Yunus": "2-1",
    "Aeden": "2-1",
    "Amine": "3-2",
    "Dai": "1-1",
    "Finley": "2-1",
    "Kevin": "2-1",
    "Ma": "1-1",
    "Noam": "2-1",
    "Rafa": "2-1",
    "Samu": "2-1",
    "Vincent": "2-1",
    "Wouter": "2-1",
    "Bart": "1-1",
    "Bo": "1-1",
    "Davy": "2-1",
    "Elay": "2-1",
    "Emin": "2-1",
    "Jorn": "1-1",
    "Kobe": "2-1",
    "Kyano": "3-2",
    "Luay": "2-2",
    "Maarten": "2-1",
    "Maher": "2-2",
    "Rohan": "2-1",
    "Santiago": "4-3",
    "Semih": "2-1",
    "Tieme": "2-1",
    "Wolf": "1-1",
    "Yassin": "2-2",
    "Antoni": "3-2",
    "Dexx": "1-1",
    "Ediz": "2-1",
    "Jacobus": "3-2",
    "Jefta": "2-1",
    "Kiyan": "2-1",
    "Koos": "2-1",
    "Lenny": "2-1",
    "Moesa": "2-1",
    "Noa": "2-1",
    "Roman": "2-2",
    "Siep": "1-1",
    "Silas": "2-1",
    "Tycho": "2-1",
    "Ziggy": "2-1",
    "Ensar": "2-1",
    "Frederik": "3-1",
    "Jent": "1-1",
    "Leendert": "2-1",
    "Merijn": "2-2",
    "Mirza": "2-1",
    "Naoufel": "2-2",
    "Royce": "1-1",
    "Teunis": "2-1",
    "Tony": "2-1",
    "Xem": "1-1",
    "Brenn": "1-1",
    "Christiaan": "3-1",
    "Flip": "1-1",
    "Lennon": "2-1",
    "Ollie": "2-1",
    "River": "2-1",
    "Rune": "2-1",
    "Shane": "1-1",
    "Sieb": "1-1",
    "Teo": "2-1",
    "Vinz": "1-1",
    "Anthony": "3-1",
    "Bjorn": "1-1",
    "Daaf": "1-1",
    "Gijsbert": "2-1",
    "Jenoah": "3-2",
    "Jibbe": "2-1",
    "Mink": "1-1",
    "Mitch": "1-1",
    "Peter": "2-1",
    "Rio": "2-1",
    "Yaman": "2-1",
    "Zev": "1-1",
    "Adrian": "3-1",
    "Aydin": "2-1",
    "Bruce": "1-1",
    "Dorian": "3-1",
    "Elia": "3-1",
    "Emil": "2-2",
    "Ilay": "2-1",
    "Milano": "3-2",
    "Navy": "2-1",
    "Nicolas": "3-1",
    "Nilo": "2-1",
    "Valentino": "4-3",
    "Yanis": "2-1",
    "Zane": "2-2",
    "Aren": "2-1",
    "Bj": "2-1",
    "Emilio": "4-2",
    "Erik": "2-1",
    "Gideon": "2-1",
    "Jakob": "2-1",
    "Jaylen": "2-1",
    "Mathias": "3-2",
    "Mauro": "2-1",
    "Maximilian": "5-3",
    "Mehmet": "2-1",
    "Micah": "2-1",
    "Na": "1-1",
    "Nathaniel": "4-2",
    "Nico": "2-1",
    "Senna": "2-1",
    "Sol": "1-1",
    "Teddy": "2-1",
    "Yasin": "2-2",
    "Yazan": "2-2",
    "Zaid": "2-2",
    "Zef": "1-1",
    "Anouar": "2-2",
    "Christian": "3-1",
    "Diaz": "2-1",
    "Dries": "1-1",
    "Goos": "1-1",
    "Kenzo": "2-1",
    "Miguel": "2-2",
    "Milas": "2-1",
    "Mousa": "2-1",
    "Sanad": "2-1",
    "Soulayman": "3-3",
    "Stefan": "2-1",
    "Thije": "2-1",
    "Yven": "2-1",
    "Zahir": "2-2",
    "Alfie": "2-1",
    "Arlo": "2-1",
    "Axel": "2-1",
    "Chester": "2-1",
    "Deen": "1-1",
    "Dies": "1-1",
    "Enes": "2-1",
    "Franciszek": "3-2",
    "Kenji": "2-1",
    "Luciano": "3-2",
    "Marius": "3-1",
    "Nassim": "2-2",
    "Philippe": "2-2",
    "Saint": "1-1",
    "Sjoerd": "1-1",
    "Tyson": "2-1",
    "Yassir": "2-2",
    "Adriaan": "3-1",
    "Anton": "2-1",
    "Caleb": "2-1",
    "Charles": "2-1",
    "Fosse": "2-1",
    "Haroun": "2-2",
    "Harun": "2-2",
    "Jorrit": "2-1",
    "Jozua": "3-1",
    "Kayden": "2-1",
    "Lennox": "2-1",
    "Mathijs": "2-2",
    "Myles": "1-1",
    "Noussair": "3-2",
    "Remy": "2-1",
    "Riven": "2-1",
    "Stenn": "1-1",
    "Tije": "2-1",
    "Alexandros": "4-1",
    "Bilal": "2-2",
    "Bradley": "2-1",
    "Faris": "2-2",
    "Hayden": "2-1",
    "Ishaan": "2-2",
    "Ishaq": "2-2",
    "Jakub": "2-1",
    "Jeremiah": "4-3",
    "Jonne": "2-1",
    "Lyo": "2-1",
    "Manoah": "3-2",
    "Menno": "2-1",
    "Selim": "2-1",
    "Umut": "2-1",
    "Vito": "2-1",
    "Yousef": "2-1",
    "Zayne": "1-1",
    "Bauke": "2-1",
    "Christopher": "3-2",
    "Dario": "3-1",
    "Devin": "2-1",
    "Emmanuel": "4-2",
    "Eren": "2-1",
    "Ja": "1-1",
    "Jairo": "2-1",
    "Kacper": "2-1",
    "Karan": "2-1",
    "Kenan": "2-1",
    "Kik": "1-1",
    "Maes": "1-1",
    "Metehan": "3-1",
    "Mikail": "3-1",
    "Nils": "1-1",
    "Safouane": "2-2",
    "Saif": "2-2",
    "Sander": "2-1",
    "Sjors": "1-1",
    "Thom": "1-1",
    "Tommie": "2-1",
    "Wessel": "2-1",
    "Zeger": "2-1",
    "Ziyad": "2-1",
    "Aidan": "2-1",
    "Aryan": "2-1",
    "Auke": "2-1",
    "Aybars": "2-1",
    "Chase": "1-1",
    "Damon": "2-1",
    "Dant": "1-1",
    "Djayden": "2-1",
    "Djoah": "2-1",
    "Dominik": "3-3",
    "Evert": "2-1",
    "Frank": "1-1",
    "Hassan": "2-1",
    "Henry": "2-1",
    "Josiah": "3-2",
    "Levv": "2-1",
    "Lu": "1-1",
    "Mete": "2-1",
    "Noeh": "1-1",
    "Oliwier": "3-3",
    "Olle": "2-1",
    "Pablo": "2-1",
    "Ray": "1-1",
    "Seven": "2-1",
    "Storm": "1-1",
    "Sultan": "2-1",
    "Theodor": "3-1",
    "Theodore": "4-3",
    "Zayan": "2-1",
    "Abdul": "2-2",
    "Adem": "2-1",
    "Alaz": "2-1",
    "Alp": "1-1",
    "Andreas": "3-2",
    "Ayan": "2-1",
    "Azad": "2-1",
    "Billy": "2-1",
    "Bobbie": "2-1",
    "Dane": "1-1",
    "Dawud": "2-2",
    "Dylano": "3-2",
    "Felipe": "3-2",
    "Gerard": "2-1",
    "Harm": "1-1",
    "Jaxon": "2-1",
    "Jippe": "2-1",
    "Jones": "1-1",
    "Joseph": "2-1",
    "Juul": "1-1",
    "Kjeld": "1-1",
    "Lucca": "2-1",
    "Marouan": "2-2",
    "Mathis": "2-1",
    "Melih": "2-1",
    "Mo": "1-1",
    "Mylan": "2-1",
    "Nael": "2-2",
    "Nio": "2-1",
    "Paul": "1-1",
    "Piet": "1-1",
    "Ries": "1-1",
    "Timur": "2-1",
    "Yannick": "2-2",
    "Arman": "2-2",
    "Gus": "1-1",
    "Jelmer": "2-1",
    "Jeremy": "3-1",
    "Jin": "1-1",
    "John": "1-1",
    "Karim": "2-2",
    "Leonard": "2-1",
    "Loan": "1-1",
    "Martin": "2-1",
    "Mathieu": "2-2",
    "Mozes": "2-1",
    "Muaz": "2-1",
    "Neo": "2-1",
    "Rafi": "2-1",
    "Talha": "2-1",
    "Timothy": "3-1",
    "Wiktor": "2-1",
    "Zavi": "2-1",
    "Antonio": "4-2",
    "Aram": "2-1",
    "Baran": "2-2",
    "Chez": "1-1",
    "Dax": "1-1",
    "Devon": "2-1",
    "Edin": "2-1",
    "Emanuel": "4-2",
    "Eric": "2-1",
    "Feis": "1-1",
    "Giel": "1-1",
    "Hasan": "2-1",
    "Ilan": "2-1",
    "Jaap": "1-1",
    "Jamal": "2-2",
    "Khalid": "2-2",
    "Krijn": "1-1",
    "Kuzey": "2-1",
    "Laith": "2-2",
    "Lino": "2-1",
    "Lo": "1-1",
    "Mahmoud": "2-1",
    "Marco": "2-1",
    "Marwan": "2-2",
    "Matheo": "3-2",
    "Matz": "1-1",
    "Maximus": "3-1",
    "Mosi": "2-1",
    "Myron": "2-1",
    "Nuaym": "2-1",
    "Osman": "2-1",
    "Ot": "1-1",
    "Rhys": "1-1",
    "Rico": "2-1",
    "Sayf": "1-1",
    "Sky": "1-1",
    "Tymon": "2-1",
    "Zeno": "2-1",
    "Aarav": "2-1",
    "Ahmet": "2-1",
    "Amos": "2-1",
    "Aran": "2-1",
    "Armin": "2-1",
    "August": "2-1",
    "Avyaan": "3-1",
    "Bastiaan": "3-1",
    "Beer": "1-1",
    "Ciro": "2-1",
    "Damin": "2-1",
    "Danilo": "3-2",
    "Danny": "2-1",
    "Efe": "2-1",
    "Elian": "3-1",
    "Eliano": "4-3",
    "Emiliano": "5-4",
    "Eray": "2-1",
    "Frans": "1-1",
    "Geert": "1-1",
    "Ilya": "3-1",
    "Jeftha": "2-1",
    "Jitse": "2-1",
    "Joost": "1-1",
    "Jude": "2-1",
    "Juli": "2-1",
    "Juup": "1-1",
    "Kayra": "2-1",
    "Keano": "2-1",
    "Khaled": "2-1",
    "Lando": "2-1",
    "Leroy": "2-1",
    "Lyon": "2-2",
    "Magnus": "2-1",
    "Maksymilian": "5-3",
    "Marciano": "3-2",
    "Matei": "2-2",
    "Mehdi": "2-1",
    "Mexx": "1-1",
    "Mischa": "2-1",
    "Nadir": "2-2",
    "Nate": "1-1",
    "Neil": "1-1",
    "Nordin": "2-1",
    "Rami": "2-1",
    "Rayen": "2-2",
    "Roy": "1-1",
    "Sabir": "2-2",
    "Salih": "2-1",
    "Salim": "2-2",
    "Sonny": "2-1",
    "Steven": "2-1",
    "Suleyman": "3-3",
    "Taim": "2-2",
    "Wesley": "2-1",
    "Yasir": "2-2",
    "Yi": "1-1",
    "Yusef": "2-1",
    "Zayden": "2-1",
    "Zyon": "2-1",
    "Abraham": "3-2",
    "Anis": "2-2",
    "Atilla": "3-2",
    "Badr": "2-1",
    "Denzel": "2-1",
    "Derk": "1-1",
    "Dorus": "2-1",
    "Eliah": "3-1",
    "Eloy": "2-1",
    "Faber": "2-1",
    "Fabio": "3-1",
    "Frenky": "2-1",
    "Gyan": "2-1",
    "Hadi": "2-1",
    "Hendrikus": "3-2",
    "Ismael": "2-1",
    "Jaimy": "2-1",
    "Janoah": "3-2",
    "Jochem": "2-1",
    "Kiran": "2-1",
    "Kobus": "2-1",
    "Mano": "2-1",
    "Mas": "1-1",
    "Mat": "1-1",
    "Merlijn": "2-2",
    "Miaz": "2-1",
    "Michiel": "2-1",
    "Musab": "2-1",
    "Neal": "2-1",
    "Nicolaas": "3-1",
    "Nuri": "2-1",
    "Poyraz": "2-1",
    "Reinier": "2-2",
    "Rick": "1-1",
    "Samir": "2-2",
    "Soufian": "3-1",
    "Tobin": "2-1",
    "Tyas": "2-1",
    "Wiebe": "2-1",
    "Wietse": "2-1",
    "Wim": "1-1",
    "Yassine": "2-2",
    "Agastya": "4-2",
    "Art": "1-1",
    "Asaf": "2-2",
    "Aymen": "2-2",
    "Benyamin": "3-1",
    "Camiel": "2-2",
    "Diem": "1-1",
    "Eduard": "3-1",
    "Elyas": "3-1",
    "Fabe": "2-1",
    "Feijs": "1-1",
    "Fenn": "1-1",
    "Givano": "3-2",
    "Hussein": "2-2",
    "Imrane": "3-1",
    "Jad": "1-1",
    "Jaivy": "2-1",
    "Jayvano": "3-2",
    "Jesaja": "3-2",
    "Joaz": "2-1",
    "Jordy": "2-1",
    "Jovi": "2-1",
    "Jozef": "2-1",
    "Juno": "2-1",
    "Just": "1-1",
    "Kaya": "2-1",
    "Keanu": "2-1",
    "Louan": "2-2",
    "Matias": "3-2",
    "Mattia": "3-2",
    "Mohamad": "4-2",
    "Noyan": "2-1",
    "Robbie": "2-1",
    "Rodin": "2-1",
    "Romeo": "3-1",
    "Saifeddine": "3-3",
    "Sietse": "2-1",
    "Silvijn": "2-2",
    "Simeon": "3-1",
    "Sion": "1-1",
    "Valerio": "4-2",
    "Zyan": "2-1",
    "Adnan": "2-1",
    "Amari": "3-2",
    "Arden": "2-2",
    "Ares": "2-1",
    "Arjan": "2-1",
    "Austin": "2-1",
    "Cem": "1-1",
    "Chahid": "2-2",
    "Darius": "3-1",
    "Denis": "2-1",
    "Dexter": "2-1",
    "Ebbe": "2-1",
    "Eddie": "2-1",
    "Elai": "3-1",
    "Fatih": "2-1",
    "Fer": "1-1",
    "Francisco": "3-2",
    "Franklin": "2-1",
    "Gavi": "2-2",
    "Gianni": "2-1",
    "Hein": "1-1",
    "Ids": "1-1",
    "Igor": "2-1",
    "Ishaaq": "2-1",
    "Jamil": "2-2",
    "Jarno": "2-1",
    "Jean": "1-1",
    "Jilles": "2-1",
    "Johnny": "2-1",
    "Julien": "3-1",
    "Kaleb": "2-1",
    "Kayne": "2-1",
    "Koa": "2-1",
    "Levin": "2-1",
    "Livay": "2-1",
    "Louk": "1-1",
    "Marnix": "2-1",
    "Marten": "2-1",
    "Nanne": "2-1",
    "Nathani": "3-2",
    "Nowen": "2-1",
    "Nyo": "2-1",
    "Olan": "2-2",
    "Ralf": "1-1",
    "Rayaan": "2-1",
    "Rinze": "2-1",
    "Rocky": "2-1",
    "Roel": "1-1",
    "Rover": "2-1",
    "Rowen": "2-1",
    "Rutger": "2-1",
    "Silvan": "2-1",
    "Syb": "1-1",
    "Thies": "1-1",
    "Timon": "2-1",
    "Yari": "2-1",
    "Yasser": "2-1",
    "Yoah": "2-1",
    "Aart": "2-1",
    "Akram": "2-1",
    "Alain": "2-2",
    "Alessio": "4-2",
    "Andr": "2-1",
    "Arend": "2-1",
    "Arne": "2-1",
    "Aurelio": "4-2",
    "Aziz": "2-2",
    "Benji": "2-1",
    "Blake": "1-1",
    "Bowe": "2-1",
    "Bowy": "2-1",
    "Brandon": "2-1",
    "Bryan": "2-1",
    "Cayden": "2-1",
    "Ché": "1-1",
    "Dailey": "2-2",
    "Dim": "1-1",
    "Dominic": "3-3",
    "Dyon": "2-2",
    "Gies": "1-1",
    "Glenn": "1-1",
    "Henk": "1-1",
    "Hessel": "2-1",
    "Hylke": "2-1",
    "Idriss": "2-1",
    "Iyad": "2-1",
    "Jiro": "2-1",
    "Jorik": "2-1",
    "Kayan": "1-1",
    "Kayn": "1-1",
    "Kick": "1-1",
    "Kudus": "2-1",
    "Layth": "1-1",
    "Leandro": "3-2",
    "Levay": "2-1",
    "Liano": "3-2",
    "Lodewijk": "3-1",
    "Maison": "2-1",
    "Miro": "2-1",
    "Mois": "1-1",
    "Nathana": "3-2",
    "Nikola": "3-1",
    "Noach": "2-1",
    "Nout": "1-1",
    "Oussaid": "2-2",
    "Pierre": "1-1",
    "Rayyan": "2-1",
    "Reinout": "2-1",
    "Renze": "2-1",
    "Rody": "2-1",
    "Rumi": "2-1",
    "Steve": "1-1",
    "Syed": "1-1",
    "Tarik": "2-1",
    "Tibo": "2-1",
    "Tomas": "2-1",
    "Uraz": "2-1",
    "Vihaan": "2-1",
    "Vinny": "2-1",
    "Walid": "2-2",
    "Ward": "1-1",
    "Xander": "2-1",
    "Zack": "1-1",
    "Adil": "2-2",
    "Adonay": "3-1",
    "Amar": "2-2",
    "Amaru": "3-2",
    "Amer": "2-2",
    "Andries": "2-1",
    "Araz": "2-2",
    "Aris": "2-1",
    "Berat": "2-2",
    "Brian": "2-1",
    "Can": "1-1",
    "Charley": "2-2",
    "Coen": "1-1",
    "Connor": "2-1",
    "Cosmo": "2-1",
    "Daniil": "2-2",
    "Devran": "2-1",
    "Diederik": "3-1",
    "Diek": "1-1",
    "Diyan": "2-1",
    "Donnie": "2-1",
    "Edward": "2-1",
    "Eliam": "3-1",
    "Elliott": "3-1",
    "Fares": "2-1",
    "Feije": "2-1",
    "Ferdi": "2-1",
    "Fes": "1-1",
    "Figo": "2-1",
    "Flint": "1-1",
    "Frits": "1-1",
    "Gianluca": "3-2",
    "Harmen": "2-1",
    "Immanuel": "4-2",
    "Imraan": "2-1",
    "Indy": "2-1",
    "Isaak": "2-1",
    "Jaiden": "2-1",
    "Jaro": "2-1",
    "Jaron": "2-1",
    "Jaxson": "2-1",
    "Jazz": "1-1",
    "Jeff": "1-1",
    "Joachim": "3-1",
    "Kas": "1-1",
    "Lemar": "2-1",
    "Lennart": "2-1",
    "Leonidas": "4-2",
    "Loeka": "2-1",
    "Matthieu": "2-2",
    "Mias": "2-1",
    "Mikael": "2-1",
    "Moses": "2-1",
    "Nadim": "2-2",
    "Nour": "1-1",
    "Nowi": "2-1",
    "Ocean": "2-1",
    "Okke": "2-1",
    "Ouassim": "2-2",
    "Ramses": "2-1",
    "Sammy": "2-1",
    "Samy": "2-1",
    "Sayfeddine": "3-3",
    "Sid": "1-1",
    "Soufiane": "2-2",
    "Stanis": "2-1",
    "Taha": "2-1",
    "Tiemen": "2-1",
    "Xemm": "1-1",
    "Yamen": "2-1",
    "Yaron": "2-1",
    "Yousri": "2-1"
}
